quicksets/__init__.py
quicksets/loader.py
tests/settings/__init__.py
tests/settings/default.py
tests/settings/develop.py
tests/settings/no_class_empty_config.py
tests/settings/not_class_public_objects.py
tests/settings/product.py
tests/settings/testing.py
tests/settings/two_alphabetic_configs.py
tests/settings/two_hidden_configs.py
tests/settings/two_not_alphabetic_configs.py
tests/settings/two_not_public_configs.py
quicksets-0.0.1.dist-info/AUTHORS
quicksets-0.0.1.dist-info/LICENSE
quicksets-0.0.1.dist-info/METADATA
quicksets-0.0.1.dist-info/WHEEL
quicksets-0.0.1.dist-info/top_level.txt
quicksets-0.0.1.dist-info/RECORD
