Metadata-Version: 2.1
Name: quicksets
Version: 0.0.1
Summary: 
Provides-Extra: dev
Requires-Dist: setuptools ; extra == 'dev'
Requires-Dist: twine ; extra == 'dev'
Requires-Dist: pytest ; extra == 'dev'
Requires-Dist: pytest-flakes ; extra == 'dev'
Requires-Dist: pytest-mock ; extra == 'dev'
Requires-Dist: pytest-cov ; extra == 'dev'
Requires-Dist: python-coveralls ; extra == 'dev'
